setup.py
miraicfg/__init__.py
miraicfg/dump.py
miraicfg.egg-info/PKG-INFO
miraicfg.egg-info/SOURCES.txt
miraicfg.egg-info/dependency_links.txt
miraicfg.egg-info/entry_points.txt
miraicfg.egg-info/requires.txt
miraicfg.egg-info/top_level.txt
miraicfg/archs/__init__.py
miraicfg/archs/arm32.py
miraicfg/archs/common.py
miraicfg/archs/x86.py
miraicfg/utils/__init__.py
miraicfg/utils/cmdline.py